affilipy/__init__.py
affilipy/affilipy.py
affilipy/amazon/__init__.py
affilipy/amazon/amazon.py
tests/__init__.py
affilipy-0.1.1.dist-info/METADATA
affilipy-0.1.1.dist-info/WHEEL
affilipy-0.1.1.dist-info/top_level.txt
affilipy-0.1.1.dist-info/RECORD
