Metadata-Version: 2.1
Name: affilipy
Version: 0.1.1
Summary: Replace other users affiliate link to own one.
Home-page: https://github.com/islands5/affilipy
Author: Islands5
Author-email: five.islands.04010613@gmail.com
License: MIT
Platform: UNKNOWN
